apss/nets/__init__.py
apss/nets/attention_model.py
apss/nets/graph_encoder.py
apss/problems/__init__.py
apss/problems/pp/problem_pp.py
apss/problems/pp/state_pp.py
apss/training/__init__.py
apss/training/apss_run.py
apss/training/generate_pp_data.py
apss/training/options.py
apss/training/reinforce_baselines_pp.py
apss/training/run_mc.py
apss/training/test.py
apss/training/train_mc.py
apss/utils/__init__.py
apss/utils/beam_search.py
apss/utils/boolmask.py
apss/utils/data_utils.py
apss/utils/functions.py
apss/utils/lexsort.py
apss/utils/log_utils.py
apss/utils/reinforce_loss.py
apss/utils/tensor_functions.py
apss-0.3.0.dist-info/METADATA
apss-0.3.0.dist-info/WHEEL
apss-0.3.0.dist-info/top_level.txt
apss-0.3.0.dist-info/RECORD
