Metadata-Version: 2.1
Name: apss
Version: 0.3.0
Summary: 一种基于神经网络和启发式策略的深度学习模型分布式训练切分(3D parallelism)快速策略搜索算法
Project-URL: Homepage, https://github.com/Cheny1m/APSS
Classifier: Programming Language :: Python :: 3
Requires-Python: >=3.7
Requires-Dist: mindspore >=2.1.1
Requires-Dist: tensorboard-logger
Requires-Dist: numpy
Requires-Dist: tqdm
